{
  "id": "7ae4acea-2863-4a7e-9822-3c79a7a57548",
  "prevId": "47207c00-0a53-45d7-93d2-f1611c996949",
  "version": "7",
  "dialect": "postgresql",
  "tables": {
    "public.certificate": {
      "name": "certificate",
      "schema": "",
      "columns": {
        "tokenHash": {
          "name": "tokenHash",
          "type": "varchar(64)",
          "primaryKey": true,
          "notNull": true
        },
        "encryptedData": {
          "name": "encryptedData",
          "type": "varchar(1000)",
          "primaryKey": false,
          "notNull": true
        },
        "issuedAt": {
          "name": "issuedAt",
          "type": "timestamp (3)",
          "primaryKey": false,
          "notNull": true
        },
        "generatedAt": {
          "name": "generatedAt",
          "type": "timestamp (3)",
          "primaryKey": false,
          "notNull": false
        },
        "tokenConsumed": {
          "name": "tokenConsumed",
          "type": "boolean",
          "primaryKey": false,
          "notNull": true,
          "default": false
        },
        "user_id": {
          "name": "user_id",
          "type": "integer",
          "primaryKey": false,
          "notNull": true
        },
        "type": {
          "name": "type",
          "type": "certificate_type",
          "typeSchema": "public",
          "primaryKey": false,
          "notNull": true,
          "default": "'higienizacao'"
        },
        "product": {
          "name": "product",
          "type": "products",
          "typeSchema": "public",
          "primaryKey": false,
          "notNull": false
        }
      },
      "indexes": {},
      "foreignKeys": {
        "certificate_user_id_user_id_fk": {
          "name": "certificate_user_id_user_id_fk",
          "tableFrom": "certificate",
          "tableTo": "user",
          "columnsFrom": [
            "user_id"
          ],
          "columnsTo": [
            "id"
          ],
          "onDelete": "no action",
          "onUpdate": "no action"
        }
      },
      "compositePrimaryKeys": {},
      "uniqueConstraints": {},
      "checkConstraints": {}
    },
    "public.token_balance": {
      "name": "token_balance",
      "schema": "",
      "columns": {
        "id": {
          "name": "id",
          "type": "serial",
          "primaryKey": true,
          "notNull": true
        },
        "type": {
          "name": "type",
          "type": "certificate_type",
          "typeSchema": "public",
          "primaryKey": false,
          "notNull": true,
          "default": "'higienizacao'"
        },
        "balance": {
          "name": "balance",
          "type": "integer",
          "primaryKey": false,
          "notNull": true,
          "default": 0
        },
        "user_id": {
          "name": "user_id",
          "type": "integer",
          "primaryKey": false,
          "notNull": true
        }
      },
      "indexes": {},
      "foreignKeys": {
        "token_balance_user_id_user_id_fk": {
          "name": "token_balance_user_id_user_id_fk",
          "tableFrom": "token_balance",
          "tableTo": "user",
          "columnsFrom": [
            "user_id"
          ],
          "columnsTo": [
            "id"
          ],
          "onDelete": "no action",
          "onUpdate": "no action"
        }
      },
      "compositePrimaryKeys": {},
      "uniqueConstraints": {
        "token_balance_user_id_type_unique": {
          "name": "token_balance_user_id_type_unique",
          "nullsNotDistinct": false,
          "columns": [
            "user_id",
            "type"
          ]
        }
      },
      "checkConstraints": {}
    },
    "public.user": {
      "name": "user",
      "schema": "",
      "columns": {
        "id": {
          "name": "id",
          "type": "integer",
          "primaryKey": true,
          "notNull": true
        },
        "createdAt": {
          "name": "createdAt",
          "type": "timestamp (3)",
          "primaryKey": false,
          "notNull": false,
          "default": "now()"
        },
        "updatedAt": {
          "name": "updatedAt",
          "type": "timestamp (3)",
          "primaryKey": false,
          "notNull": false,
          "default": "now()"
        }
      },
      "indexes": {},
      "foreignKeys": {},
      "compositePrimaryKeys": {},
      "uniqueConstraints": {},
      "checkConstraints": {}
    }
  },
  "enums": {
    "public.certificate_type": {
      "name": "certificate_type",
      "schema": "public",
      "values": [
        "higienizacao",
        "impermeabilizacao"
      ]
    },
    "public.products": {
      "name": "products",
      "schema": "public",
      "values": [
        "Impertudo",
        "Safe",
        "Safe Tech",
        "Eco",
        "Tech Block"
      ]
    }
  },
  "schemas": {},
  "sequences": {},
  "views": {},
  "_meta": {
    "columns": {},
    "schemas": {},
    "tables": {}
  }
}